CHANGELOG.rst
MANIFEST.in
README.rst
setup.cfg
setup.py
kafka_logger/__init__.py
logwatcher_kafka_plugin.egg-info/PKG-INFO
logwatcher_kafka_plugin.egg-info/SOURCES.txt
logwatcher_kafka_plugin.egg-info/dependency_links.txt
logwatcher_kafka_plugin.egg-info/not-zip-safe
logwatcher_kafka_plugin.egg-info/requires.txt
logwatcher_kafka_plugin.egg-info/top_level.txt