Metadata-Version: 1.1
Name: logwatcher-kafka-plugin
Version: 1.0
Summary: LogWatcher Plugin for Sending log lines to a Kafka Topic
Home-page: UNKNOWN
Author: Wil Heitritter
Author-email: no-reply@noreply.com
License: Apache
Keywords: Logs Metrics Access Apache Ganglia Graphite devops Kafka Logstash
Platform: UNKNOWN
Classifier: Programming Language :: Python
Classifier: Programming Language :: Python :: 2.7
Classifier: Intended Audience :: System Administrators 
